Metadata-Version: 2.1
Name: pathhistogram
Version: 1.0.0
Summary: A tool to generate histograms of file-sizes
Home-page: https://github.com/dsoprea/pathhistogram
Author: Dustin Oprea
Author-email: myselfasunder@gmail.com
License: GPL 2
Platform: UNKNOWN
